[
    {
        "exitcode": 1,
        "id": "136.727",
        "name": "RunDoubleEGPrpt2016B+RunDoubleEGPrpt2016B+HLTDR2_2016+RECODR2_2016reHLT+HARVESTDR2",
        "steps": [
            {
                "errors": 0,
                "status": "DAS_ERROR",
                "warnings": 0
            },
            {
                "errors": -1,
                "status": "NOTRUN",
                "warnings": -1
            },
            {
                "errors": -1,
                "status": "NOTRUN",
                "warnings": -1
            },
            {
                "errors": -1,
                "status": "NOTRUN",
                "warnings": -1
            }
        ]
    },
    {
        "exitcode": 1,
        "id": "140.53",
        "name": "RunHI2011+RunHI2011+RECOHID11+HARVESTDHI",
        "steps": [
            {
                "errors": 0,
                "status": "DAS_ERROR",
                "warnings": 0
            },
            {
                "errors": -1,
                "status": "NOTRUN",
                "warnings": -1
            },
            {
                "errors": -1,
                "status": "NOTRUN",
                "warnings": -1
            }
        ]
    },
    {
        "exitcode": 1,
        "id": "1004.0",
        "name": "RunHI2011+RunHI2011+TIER0EXPHI+ALCAEXPHI+ALCAHARVD1HI+ALCAHARVD2HI+ALCAHARVD3HI+ALCAHARVD5HI",
        "steps": [
            {
                "errors": 0,
                "status": "DAS_ERROR",
                "warnings": 0
            },
            {
                "errors": -1,
                "status": "NOTRUN",
                "warnings": -1
            },
            {
                "errors": -1,
                "status": "NOTRUN",
                "warnings": -1
            },
            {
                "errors": -1,
                "status": "NOTRUN",
                "warnings": -1
            },
            {
                "errors": -1,
                "status": "NOTRUN",
                "warnings": -1
            },
            {
                "status": "NOTRUN"
            },
            {
                "status": "NOTRUN"
            }
        ]
    },
    {
        "exitcode": 1,
        "id": "250205.0",
        "name": "ZTT_13+ZTT_13INPUT+DIGIPRMXUP15_PU25+RECOPRMXUP15_PU25+HARVESTUP15_PU25",
        "steps": [
            {
                "errors": 0,
                "status": "DAS_ERROR",
                "warnings": 0
            },
            {
                "errors": -1,
                "status": "NOTRUN",
                "warnings": -1
            },
            {
                "errors": -1,
                "status": "NOTRUN",
                "warnings": -1
            },
            {
                "errors": -1,
                "status": "NOTRUN",
                "warnings": -1
            }
        ]
    },
    {
        "exitcode": 1,
        "id": "500205.0",
        "name": "ZTT_13+ZTT_13INPUT+DIGIPRMXUP15_PU50+RECOPRMXUP15_PU50+HARVESTUP15_PU50",
        "steps": [
            {
                "errors": 0,
                "status": "DAS_ERROR",
                "warnings": 0
            },
            {
                "errors": -1,
                "status": "NOTRUN",
                "warnings": -1
            },
            {
                "errors": -1,
                "status": "NOTRUN",
                "warnings": -1
            },
            {
                "errors": -1,
                "status": "NOTRUN",
                "warnings": -1
            }
        ]
    },
    {
        "exitcode": 16640,
        "id": "4.78",
        "name": "WElSkim2012D+WElSkim2012D+HLTDSKIM+RECODR1reHLT+HARVESTDR1reHLT",
        "steps": [
            {
                "errors": 0,
                "status": "PASSED",
                "warnings": 0
            },
            {
                "errors": 0,
                "status": "PASSED",
                "warnings": 106
            },
            {
                "errors": 4,
                "status": "FAILED",
                "warnings": 6
            },
            {
                "errors": -1,
                "status": "NOTRUN",
                "warnings": -1
            }
        ]
    },
    {
        "exitcode": 16640,
        "id": "11024.0",
        "name": "TTbar_13+TTbar_13TeV_TuneCUETP8M1_2023LReco_GenSimFull+DigiFull_2023LReco+RecoFullLocal_2023LReco",
        "steps": [
            {
                "errors": 0,
                "status": "PASSED",
                "warnings": 54
            },
            {
                "errors": 0,
                "status": "PASSED",
                "warnings": 106
            },
            {
                "errors": 0,
                "status": "FAILED",
                "warnings": 0
            }
        ]
    },
    {
        "exitcode": 0,
        "id": "5.1",
        "name": "TTbar+TTbarFS+HARVESTFS",
        "steps": [
            {
                "errors": 0,
                "status": "PASSED",
                "warnings": 424
            },
            {
                "errors": 7,
                "status": "PASSED",
                "warnings": 5
            }
        ]
    },
    {
        "exitcode": 0,
        "id": "5.2",
        "name": "SingleMuPt10+SingleMuPt10FS+HARVESTFS",
        "steps": [
            {
                "errors": 0,
                "status": "PASSED",
                "warnings": 350
            },
            {
                "errors": 7,
                "status": "PASSED",
                "warnings": 5
            }
        ]
    },
    {
        "exitcode": 0,
        "id": "5.3",
        "name": "SingleMuPt100+SingleMuPt100FS+HARVESTFS",
        "steps": [
            {
                "errors": 0,
                "status": "PASSED",
                "warnings": 487
            },
            {
                "errors": 7,
                "status": "PASSED",
                "warnings": 5
            }
        ]
    },
    {
        "exitcode": 0,
        "id": "5.4",
        "name": "ZEE+ZEEFS+HARVESTFS",
        "steps": [
            {
                "errors": 0,
                "status": "PASSED",
                "warnings": 81
            },
            {
                "errors": 7,
                "status": "PASSED",
                "warnings": 5
            }
        ]
    },
    {
        "exitcode": 0,
        "id": "5.5",
        "name": "ZTT+ZTTFS+HARVESTFS",
        "steps": [
            {
                "errors": 0,
                "status": "PASSED",
                "warnings": 135
            },
            {
                "errors": 7,
                "status": "PASSED",
                "warnings": 5
            }
        ]
    },
    {
        "exitcode": 0,
        "id": "5.6",
        "name": "QCD_FlatPt_15_3000+QCDFlatPt153000FS+HARVESTFS",
        "steps": [
            {
                "errors": 0,
                "status": "PASSED",
                "warnings": 249
            },
            {
                "errors": 7,
                "status": "PASSED",
                "warnings": 5
            }
        ]
    },
    {
        "exitcode": 0,
        "id": "7.0",
        "name": "Cosmics+Cosmics+DIGICOS+RECOCOS+ALCACOS+HARVESTCOS",
        "steps": [
            {
                "errors": 0,
                "status": "PASSED",
                "warnings": 6
            },
            {
                "errors": 0,
                "status": "PASSED",
                "warnings": 0
            },
            {
                "errors": 0,
                "status": "PASSED",
                "warnings": 0
            },
            {
                "errors": 0,
                "status": "PASSED",
                "warnings": 0
            },
            {
                "errors": 5,
                "status": "PASSED",
                "warnings": 12
            }
        ]
    },
    {
        "exitcode": 0,
        "id": "7.1",
        "name": "CosmicsSPLoose+CosmicsSPLoose+DIGICOS+RECOCOS+ALCACOS+HARVESTCOS",
        "steps": [
            {
                "errors": 0,
                "status": "PASSED",
                "warnings": 1
            },
            {
                "errors": 0,
                "status": "PASSED",
                "warnings": 0
            },
            {
                "errors": 0,
                "status": "PASSED",
                "warnings": 0
            },
            {
                "errors": 0,
                "status": "PASSED",
                "warnings": 0
            },
            {
                "errors": 5,
                "status": "PASSED",
                "warnings": 12
            }
        ]
    },
    {
        "exitcode": 0,
        "id": "103.0",
        "name": "InclusiveppMuX+InclusiveppMuX+DIGI+RECO",
        "steps": [
            {
                "errors": 0,
                "status": "PASSED",
                "warnings": 8
            },
            {
                "errors": 0,
                "status": "PASSED",
                "warnings": 0
            },
            {
                "errors": 0,
                "status": "PASSED",
                "warnings": 1
            }
        ]
    },
    {
        "exitcode": 0,
        "id": "106.0",
        "name": "bJpsiX+bJpsiX+DIGI+RECO",
        "steps": [
            {
                "errors": 0,
                "status": "PASSED",
                "warnings": 9
            },
            {
                "errors": 0,
                "status": "PASSED",
                "warnings": 0
            },
            {
                "errors": 0,
                "status": "PASSED",
                "warnings": 1
            }
        ]
    },
    {
        "exitcode": 0,
        "id": "110.0",
        "name": "SingleTauPt50Pythia+SingleTauPt50Pythia+DIGI+RECO",
        "steps": [
            {
                "errors": 0,
                "status": "PASSED",
                "warnings": 27
            },
            {
                "errors": 0,
                "status": "PASSED",
                "warnings": 51
            },
            {
                "errors": 20,
                "status": "PASSED",
                "warnings": 427
            }
        ]
    },
    {
        "exitcode": 0,
        "id": "120.0",
        "name": "SinglePi0E10+SinglePi0E10+DIGI+RECO",
        "steps": [
            {
                "errors": 0,
                "status": "PASSED",
                "warnings": 45
            },
            {
                "errors": 0,
                "status": "PASSED",
                "warnings": 34
            },
            {
                "errors": 20,
                "status": "PASSED",
                "warnings": 312
            }
        ]
    },
    {
        "exitcode": 0,
        "id": "122.0",
        "name": "UpsMM+UpsMM+DIGI+RECO",
        "steps": [
            {
                "errors": 0,
                "status": "PASSED",
                "warnings": 26
            },
            {
                "errors": 0,
                "status": "PASSED",
                "warnings": 0
            },
            {
                "errors": 4,
                "status": "PASSED",
                "warnings": 14
            }
        ]
    },
    {
        "exitcode": 0,
        "id": "123.1",
        "name": "QCD_Pt_80_120+QCD_Pt_80_120FS",
        "steps": [
            {
                "errors": 0,
                "status": "PASSED",
                "warnings": 323
            }
        ]
    },
    {
        "exitcode": 0,
        "id": "123.2",
        "name": "QCD_Pt_3000_3500+QCD_Pt_3000_3500FS",
        "steps": [
            {
                "errors": 0,
                "status": "PASSED",
                "warnings": 699
            }
        ]
    },
    {
        "exitcode": 0,
        "id": "124.2",
        "name": "ZTT+ZTTFS",
        "steps": [
            {
                "errors": 0,
                "status": "PASSED",
                "warnings": 211
            }
        ]
    },
    {
        "exitcode": 0,
        "id": "128.0",
        "name": "SingleMuPt1HS+SingleMuPt1HS+DIGI+RECO",
        "steps": [
            {
                "errors": 0,
                "status": "PASSED",
                "warnings": 22
            },
            {
                "errors": 0,
                "status": "PASSED",
                "warnings": 17
            },
            {
                "errors": 20,
                "status": "PASSED",
                "warnings": 197
            }
        ]
    },
    {
        "exitcode": 0,
        "id": "130.0",
        "name": "SinglePiPt10+SinglePiPt10+DIGI+RECO",
        "steps": [
            {
                "errors": 0,
                "status": "PASSED",
                "warnings": 49
            },
            {
                "errors": 0,
                "status": "PASSED",
                "warnings": 7
            },
            {
                "errors": 20,
                "status": "PASSED",
                "warnings": 151
            }
        ]
    },
    {
        "exitcode": 0,
        "id": "134.813",
        "name": "RunCosmics2015C+RunCosmics2015C+RECOCOSDRUN2+ALCACOSDRUN2+HARVESTDCRUN2",
        "steps": [
            {
                "errors": 0,
                "status": "PASSED",
                "warnings": 0
            },
            {
                "errors": 3,
                "status": "PASSED",
                "warnings": 976
            },
            {
                "errors": 0,
                "status": "PASSED",
                "warnings": 84
            },
            {
                "errors": 5,
                "status": "PASSED",
                "warnings": 12
            }
        ]
    },
    {
        "exitcode": 0,
        "id": "135.13",
        "name": "TTbar_13+TTbarFS_13_trackingOnlyValidation+HARVESTUP15FS_trackingOnly",
        "steps": [
            {
                "errors": 1,
                "status": "PASSED",
                "warnings": 10
            },
            {
                "errors": 6,
                "status": "PASSED",
                "warnings": 11
            }
        ]
    },
    {
        "exitcode": 0,
        "id": "136.722",
        "name": "RunDoubleEG2016B+RunDoubleEG2016B+HLTDR2_2016+RECODR2_2016reHLT_skimDoubleEG+HARVESTDR2",
        "steps": [
            {
                "errors": 0,
                "status": "PASSED",
                "warnings": 0
            },
            {
                "errors": 2,
                "status": "PASSED",
                "warnings": 915
            },
            {
                "errors": 541,
                "status": "PASSED",
                "warnings": 4193
            },
            {
                "errors": 0,
                "status": "PASSED",
                "warnings": 9
            }
        ]
    },
    {
        "exitcode": 0,
        "id": "136.723",
        "name": "RunDoubleMuon2016B+RunDoubleMuon2016B+HLTDR2_2016+RECODR2_2016reHLT+HARVESTDR2",
        "steps": [
            {
                "errors": 0,
                "status": "PASSED",
                "warnings": 0
            },
            {
                "errors": 2,
                "status": "PASSED",
                "warnings": 567
            },
            {
                "errors": 518,
                "status": "PASSED",
                "warnings": 892
            },
            {
                "errors": 0,
                "status": "PASSED",
                "warnings": 9
            }
        ]
    },
    {
        "exitcode": 0,
        "id": "136.726",
        "name": "RunMuonEG2016B+RunMuonEG2016B+HLTDR2_2016+RECODR2_2016reHLT_skimMuonEG+HARVESTDR2",
        "steps": [
            {
                "errors": 0,
                "status": "PASSED",
                "warnings": 0
            },
            {
                "errors": 4,
                "status": "PASSED",
                "warnings": 1282
            },
            {
                "errors": 507,
                "status": "PASSED",
                "warnings": 1907
            },
            {
                "errors": 0,
                "status": "PASSED",
                "warnings": 9
            }
        ]
    },
    {
        "exitcode": 0,
        "id": "136.728",
        "name": "RunSingleMuPrpt2016B+RunSingleMuPrpt2016B+HLTDR2_2016+RECODR2_2016reHLT+HARVESTDR2",
        "steps": [
            {
                "errors": 0,
                "status": "PASSED",
                "warnings": 0
            },
            {
                "errors": 2,
                "status": "PASSED",
                "warnings": 246
            },
            {
                "errors": 484,
                "status": "PASSED",
                "warnings": 1999
            },
            {
                "errors": 0,
                "status": "PASSED",
                "warnings": 9
            }
        ]
    },
    {
        "exitcode": 0,
        "id": "136.729",
        "name": "RunSingleEl2016B+RunSingleEl2016B+HLTDR2_2016+RECODR2_2016reHLT+HARVESTDR2",
        "steps": [
            {
                "errors": 0,
                "status": "PASSED",
                "warnings": 0
            },
            {
                "errors": 2,
                "status": "PASSED",
                "warnings": 317
            },
            {
                "errors": 449,
                "status": "PASSED",
                "warnings": 559
            },
            {
                "errors": 0,
                "status": "PASSED",
                "warnings": 9
            }
        ]
    },
    {
        "exitcode": 0,
        "id": "136.73",
        "name": "RunSingleMu2016B+RunSingleMu2016B+HLTDR2_2016+RECODR2_2016reHLT_skimSingleMu+HARVESTDR2",
        "steps": [
            {
                "errors": 0,
                "status": "PASSED",
                "warnings": 0
            },
            {
                "errors": 2,
                "status": "PASSED",
                "warnings": 780
            },
            {
                "errors": 495,
                "status": "PASSED",
                "warnings": 1827
            },
            {
                "errors": 0,
                "status": "PASSED",
                "warnings": 9
            }
        ]
    },
    {
        "exitcode": 0,
        "id": "140.2",
        "name": "PhotonJets_Pt_10_13_HI+PhotonJets_Pt_10_13_HIINPUT+DIGIHI+RECOHI+HARVESTHI",
        "steps": [
            {
                "errors": 0,
                "status": "PASSED",
                "warnings": 0
            },
            {
                "errors": 1,
                "status": "PASSED",
                "warnings": 41
            },
            {
                "errors": 31,
                "status": "PASSED",
                "warnings": 65
            },
            {
                "errors": 5,
                "status": "PASSED",
                "warnings": 10
            }
        ]
    },
    {
        "exitcode": 0,
        "id": "140.4",
        "name": "ZEEMM_13_HI+ZEEMM_13_HIINPUT+DIGIHI+RECOHI+HARVESTHI",
        "steps": [
            {
                "errors": 0,
                "status": "PASSED",
                "warnings": 0
            },
            {
                "errors": 1,
                "status": "PASSED",
                "warnings": 50
            },
            {
                "errors": 29,
                "status": "PASSED",
                "warnings": 166
            },
            {
                "errors": 5,
                "status": "PASSED",
                "warnings": 10
            }
        ]
    },
    {
        "exitcode": 0,
        "id": "520.0",
        "name": "VHToHtt_NLO_Pow_13TeV_py8_taurhonu+VHToH_Pow_LHE_13TeV+Hadronizer_TuneCUETP8M1_13TeV_Httrhonu_powhegEmissionVeto_pythia8+HARVESTGEN2",
        "steps": [
            {
                "errors": 0,
                "status": "PASSED",
                "warnings": 14
            },
            {
                "errors": 0,
                "status": "PASSED",
                "warnings": 25
            },
            {
                "errors": 0,
                "status": "PASSED",
                "warnings": 0
            }
        ]
    },
    {
        "exitcode": 0,
        "id": "523.0",
        "name": "TTbar012Jets_NLO_Mad_13TeV_py8_Evt+TTbar012Jets_5f_NLO_FXFX_Madgraph_LHE_13TeV+Hadronizer_TuneCUETP8M1_13TeV_aMCatNLO_FXFX_5f_max2j_max1p_LHE_pythia8_evtgen+HARVESTGEN2",
        "steps": [
            {
                "errors": 0,
                "status": "PASSED",
                "warnings": 9
            },
            {
                "errors": 0,
                "status": "PASSED",
                "warnings": 47
            },
            {
                "errors": 0,
                "status": "PASSED",
                "warnings": 0
            }
        ]
    },
    {
        "exitcode": 0,
        "id": "524.0",
        "name": "VHToHtt_NLO_Pow_13TeV_py8_Ta+VHToH_Pow_LHE_13TeV+Hadronizer_TuneCUETP8M1_13TeV_Htt_powhegEmissionVeto_pythia8_tauola+HARVESTGEN2",
        "steps": [
            {
                "errors": 0,
                "status": "PASSED",
                "warnings": 14
            },
            {
                "errors": 0,
                "status": "PASSED",
                "warnings": 26
            },
            {
                "errors": 0,
                "status": "PASSED",
                "warnings": 0
            }
        ]
    },
    {
        "exitcode": 0,
        "id": "527.0",
        "name": "VHToHtt_NLO_Pow_13TeV_py8_Ta_taupinu+VHToH_Pow_LHE_13TeV+Hadronizer_TuneCUETP8M1_13TeV_Httpinu_powhegEmissionVeto_pythia8_tauola+HARVESTGEN2",
        "steps": [
            {
                "errors": 0,
                "status": "PASSED",
                "warnings": 14
            },
            {
                "errors": 0,
                "status": "PASSED",
                "warnings": 28
            },
            {
                "errors": 0,
                "status": "PASSED",
                "warnings": 0
            }
        ]
    },
    {
        "exitcode": 0,
        "id": "530.0",
        "name": "VHToHtt_NLO_Pow_13TeV_py8_Ta_taurhonu+VHToH_Pow_LHE_13TeV+Hadronizer_TuneCUETP8M1_13TeV_Httrhonu_powhegEmissionVeto_pythia8_tauola+HARVESTGEN2",
        "steps": [
            {
                "errors": 0,
                "status": "PASSED",
                "warnings": 13
            },
            {
                "errors": 0,
                "status": "PASSED",
                "warnings": 38
            },
            {
                "errors": 0,
                "status": "PASSED",
                "warnings": 0
            }
        ]
    },
    {
        "exitcode": 0,
        "id": "551.0",
        "name": "TTbar012Jets_NLO_Mad_13TeV_py8+TTbar012Jets_5f_NLO_FXFX_Madgraph_LHE_13TeV+Hadronizer_TuneCUETP8M1_13TeV_aMCatNLO_FXFX_5f_max2j_max1p_LHE_pythia8+HARVESTGEN2",
        "steps": [
            {
                "errors": 0,
                "status": "PASSED",
                "warnings": 15
            },
            {
                "errors": 0,
                "status": "PASSED",
                "warnings": 23
            },
            {
                "errors": 0,
                "status": "PASSED",
                "warnings": 0
            }
        ]
    },
    {
        "exitcode": 0,
        "id": "552.0",
        "name": "VHToHtt_NLO_Pow_13TeV_py8+VHToH_Pow_LHE_13TeV+Hadronizer_TuneCUETP8M1_13TeV_Htt_powhegEmissionVeto_pythia8+HARVESTGEN2",
        "steps": [
            {
                "errors": 0,
                "status": "PASSED",
                "warnings": 13
            },
            {
                "errors": 0,
                "status": "PASSED",
                "warnings": 23
            },
            {
                "errors": 0,
                "status": "PASSED",
                "warnings": 0
            }
        ]
    },
    {
        "exitcode": 0,
        "id": "555.0",
        "name": "DYTollJets_NLO_Mad_13TeV_py8+DYToll012Jets_5f_NLO_FXFX_Madgraph_LHE_13TeV+Hadronizer_TuneCUETP8M1_13TeV_aMCatNLO_FXFX_5f_max2j_max0p_LHE_pythia8+HARVESTGEN2",
        "steps": [
            {
                "errors": 0,
                "status": "PASSED",
                "warnings": 14
            },
            {
                "errors": 0,
                "status": "PASSED",
                "warnings": 21
            },
            {
                "errors": 0,
                "status": "PASSED",
                "warnings": 0
            }
        ]
    },
    {
        "exitcode": 0,
        "id": "1356.0",
        "name": "ZEE_13_DBLMINIAOD+ZEE_13_DBLMINIAOD+DIGIUP15+RECOAODUP15+HARVESTUP15+DBLMINIAODMCUP15NODQM",
        "steps": [
            {
                "errors": 0,
                "status": "PASSED",
                "warnings": 75
            },
            {
                "errors": 1,
                "status": "PASSED",
                "warnings": 357
            },
            {
                "errors": 52,
                "status": "PASSED",
                "warnings": 148
            },
            {
                "errors": 0,
                "status": "PASSED",
                "warnings": 9
            },
            {
                "errors": 0,
                "status": "PASSED",
                "warnings": 86
            }
        ]
    },
    {
        "exitcode": 0,
        "id": "1363.0",
        "name": "VBFHToBB_M125_Pow_py8_Evt_13+VBFHToBB_M125_Pow_py8_Evt_13+DIGIUP15+RECOUP15+HARVESTUP15",
        "steps": [
            {
                "errors": 0,
                "status": "PASSED",
                "warnings": 85
            },
            {
                "errors": 1,
                "status": "PASSED",
                "warnings": 172
            },
            {
                "errors": 76,
                "status": "PASSED",
                "warnings": 388
            },
            {
                "errors": 0,
                "status": "PASSED",
                "warnings": 9
            }
        ]
    },
    {
        "exitcode": 0,
        "id": "4007.0",
        "name": "QCD_Pt_30_80_BCtoE_8TeV+QCD_Pt_30_80_BCtoE_8TeV+DIGIPU1+RECOPUDBG",
        "steps": [
            {
                "errors": 0,
                "status": "PASSED",
                "warnings": 27
            },
            {
                "errors": 0,
                "status": "PASSED",
                "warnings": 0
            },
            {
                "errors": 7,
                "status": "PASSED",
                "warnings": 14
            }
        ]
    },
    {
        "exitcode": 0,
        "id": "10024.1",
        "name": "TTbar_13+TTbar_13TeV_TuneCUETP8M1_2017_GenSimFullINPUT+DigiFull_2017+RecoFull_trackingOnly_2017+HARVESTFull_trackingOnly_2017",
        "steps": [
            {
                "errors": 0,
                "status": "PASSED",
                "warnings": 0
            },
            {
                "errors": 1,
                "status": "PASSED",
                "warnings": 176
            },
            {
                "errors": 0,
                "status": "PASSED",
                "warnings": 208
            },
            {
                "errors": 1,
                "status": "PASSED",
                "warnings": 8
            }
        ]
    },
    {
        "exitcode": 0,
        "id": "10024.5",
        "name": "TTbar_13+TTbar_13TeV_TuneCUETP8M1_2017_GenSimFullINPUT+DigiFull_2017+RecoFull_trackingOnlyPhase1PU70_2017+HARVESTFull_trackingOnly_2017",
        "steps": [
            {
                "errors": 0,
                "status": "PASSED",
                "warnings": 0
            },
            {
                "errors": 1,
                "status": "PASSED",
                "warnings": 119
            },
            {
                "errors": 0,
                "status": "PASSED",
                "warnings": 195
            },
            {
                "errors": 1,
                "status": "PASSED",
                "warnings": 8
            }
        ]
    },
    {
        "exitcode": 0,
        "id": "25202.0",
        "name": "TTbar_13+TTbar_13INPUT+DIGIUP15_PU25+RECOUP15_PU25+HARVESTUP15_PU25",
        "steps": [
            {
                "errors": 0,
                "status": "PASSED",
                "warnings": 0
            },
            {
                "errors": 1,
                "status": "PASSED",
                "warnings": 2458
            },
            {
                "errors": 103,
                "status": "PASSED",
                "warnings": 1306
            },
            {
                "errors": 0,
                "status": "PASSED",
                "warnings": 9
            }
        ]
    },
    {
        "exitcode": 0,
        "id": "25204.0",
        "name": "QQH1352T_13+QQH1352T_13INPUT+DIGIUP15_PU25+RECOUP15_PU25+HARVESTUP15_PU25",
        "steps": [
            {
                "errors": 0,
                "status": "PASSED",
                "warnings": 0
            },
            {
                "errors": 1,
                "status": "PASSED",
                "warnings": 1162
            },
            {
                "errors": 54,
                "status": "PASSED",
                "warnings": 907
            },
            {
                "errors": 0,
                "status": "PASSED",
                "warnings": 9
            }
        ]
    },
    {
        "exitcode": 0,
        "id": "25208.0",
        "name": "SMS-T1tttt_mGl-1500_mLSP-100_13+SMS-T1tttt_mGl-1500_mLSP-100_13INPUT+DIGIUP15_PU25+RECOUP15_PU25+HARVESTUP15_PU25",
        "steps": [
            {
                "errors": 0,
                "status": "PASSED",
                "warnings": 0
            },
            {
                "errors": 9,
                "status": "PASSED",
                "warnings": 917
            },
            {
                "errors": 229,
                "status": "PASSED",
                "warnings": 1163
            },
            {
                "errors": 0,
                "status": "PASSED",
                "warnings": 9
            }
        ]
    },
    {
        "exitcode": 0,
        "id": "25209.0",
        "name": "QCD_FlatPt_15_3000HS_13+QCD_FlatPt_15_3000HS_13INPUT+DIGIUP15_PU25+RECOUP15_PU25+HARVESTUP15_PU25",
        "steps": [
            {
                "errors": 0,
                "status": "PASSED",
                "warnings": 0
            },
            {
                "errors": 1,
                "status": "PASSED",
                "warnings": 1963
            },
            {
                "errors": 97,
                "status": "PASSED",
                "warnings": 1522
            },
            {
                "errors": 0,
                "status": "PASSED",
                "warnings": 9
            }
        ]
    }
]
